libchronos.a
libchronos.so
chronos/__init__.py
chronos/libchronos.so
chronos/multiprocessing.py
chronos/stub.py
chronos_gpu-1.1.0.dist-info/licenses/LICENSE
chronos_gpu-1.1.0.dist-info/METADATA
chronos_gpu-1.1.0.dist-info/WHEEL
chronos_gpu-1.1.0.dist-info/top_level.txt
chronos_gpu-1.1.0.dist-info/RECORD
